pysenteishon/__init__.py
pysenteishon/src/__init__.py
pysenteishon/src/app.py
pysenteishon/src/static/index.html
pysenteishon/src/static/css/bootstrap.min.css
pysenteishon/src/static/css/font-awesome.min.css
pysenteishon/src/static/css/main.css
pysenteishon/src/static/fonts/FontAwesome.otf
pysenteishon/src/static/fonts/fontawesome-webfont.eot
pysenteishon/src/static/fonts/fontawesome-webfont.svg
pysenteishon/src/static/fonts/fontawesome-webfont.ttf
pysenteishon/src/static/fonts/fontawesome-webfont.woff
pysenteishon/src/static/fonts/glyphicons-halflings-regular.eot
pysenteishon/src/static/fonts/glyphicons-halflings-regular.svg
pysenteishon/src/static/fonts/glyphicons-halflings-regular.ttf
pysenteishon/src/static/fonts/glyphicons-halflings-regular.woff
pysenteishon/src/static/js/bootstrap.min.js
pysenteishon/src/static/js/jquery-2.1.1.min.js
pysenteishon/src/static/js/jquery.touchSwipe.min.js
pysenteishon/src/static/js/pysenteishon.js
pysenteishon/src/static/js/qrcode.min.js
pysenteishon-1.0.0b1.dist-info/DESCRIPTION.rst
pysenteishon-1.0.0b1.dist-info/METADATA
pysenteishon-1.0.0b1.dist-info/RECORD
pysenteishon-1.0.0b1.dist-info/WHEEL
pysenteishon-1.0.0b1.dist-info/entry_points.txt
pysenteishon-1.0.0b1.dist-info/metadata.json
pysenteishon-1.0.0b1.dist-info/top_level.txt
