Metadata-Version: 2.0
Name: pysenteishon
Version: 1.0.0b1
Summary: Control your presentations swiping your touchscreen!
Home-page: https://github.com/edvm/pysenteishon
Author: Manuel Kaufmann
Author-email: humitos@gmail.com
License: GPLv3
Keywords: presentation touchscreen talk pycon conference
Platform: UNKNOWN
Classifier: Development Status :: 4 - Beta
Classifier: Environment :: Console
Classifier: Environment :: Web Environment
Classifier: Intended Audience :: End Users/Desktop
Classifier: License :: OSI Approved :: GNU General Public License v3 (GPLv3)
Classifier: Operating System :: Unix
Classifier: Programming Language :: Python
Classifier: Programming Language :: Python :: 3
Classifier: Programming Language :: Python :: 3.2
Classifier: Programming Language :: Python :: 3.3
Classifier: Programming Language :: Python :: 3.4
Classifier: Programming Language :: Python :: 3.5
Classifier: Topic :: Communications :: Conferencing
Requires-Dist: PyUserInput
Requires-Dist: cherrypy
Requires-Dist: netifaces
Requires-Dist: python3-xlib
